hourcounter/__init__.py
hourcounter/hourcounter.py
hourcounter-0.0.7.dist-info/METADATA
hourcounter-0.0.7.dist-info/WHEEL
hourcounter-0.0.7.dist-info/top_level.txt
hourcounter-0.0.7.dist-info/RECORD
