Metadata-Version: 2.1
Name: hourcounter
Version: 0.0.7
Summary: Count the number of items in the time interval
Home-page: UNKNOWN
Author: Davuluri Hemanth Chowdary
Author-email: hemanthdavuluri98@gmail.com
License: UNKNOWN
Platform: UNKNOWN
